<?xml version="1.0" encoding="UTF-8" standalone="yes"?>
<taskListWrapper>
    <Task>
        <description>123</description>
        <duedate>2021-01-27</duedate>
        <isCompleted>true</isCompleted>
    </Task>
    <Task>
        <description>213</description>
        <duedate>2020-10-29</duedate>
        <isCompleted>false</isCompleted>
    </Task>
    <Task>
        <description>Test</description>
        <duedate>1960-01-29</duedate>
        <isCompleted>true</isCompleted>
    </Task>
    <Task>
        <description>123</description>
        <duedate>2020-10-31</duedate>
        <isCompleted>true</isCompleted>
    </Task>
</taskListWrapper>
